{"cameraMode":{"drawMode":0,"name":"Shaded","section":"Shading Mode"},"sceneLighting":false,"audioPlay":false,"sceneViewState":{"m_AlwaysRefresh":false,"showFog":true,"showSkybox":false,"showFlares":true,"showImageEffects":true,"showParticleSystems":true,"showVisualEffectGraphs":true,"m_FxEnabled":true},"in2DMode":false,"pivot":{"x":-16.467403411865236,"y":2.720026969909668,"z":-35.69001007080078},"rotation":{"x":0.17814220488071443,"y":0.09783098846673966,"z":-0.017802074551582338,"w":0.9789683818817139},"size":12.295526504516602,"orthographic":false}